opensignals/__about__.py
opensignals/__init__.py
opensignals/__main__.py
opensignals/features.py
opensignals/utils.py
opensignals/data/__init__.py
opensignals/data/provider.py
opensignals/data/yahoo.py
opensignals-0.0.5.post1.dist-info/LICENSE
opensignals-0.0.5.post1.dist-info/METADATA
opensignals-0.0.5.post1.dist-info/WHEEL
opensignals-0.0.5.post1.dist-info/entry_points.txt
opensignals-0.0.5.post1.dist-info/top_level.txt
opensignals-0.0.5.post1.dist-info/zip-safe
opensignals-0.0.5.post1.dist-info/RECORD
