Metadata-Version: 2.1
Name: opensignals
Version: 0.0.5.post1
Summary: Open Signals
Home-page: https://github.com/councilofelders/opensignals
Author: Jordi Villar
Author-email: jrdi.villar@gmail.com
License: Apache License
Project-URL: Bug Tracker, https://github.com/councilofelders/opensignals/issues
Classifier: License :: OSI Approved :: Apache Software License
Classifier: Development Status :: 3 - Alpha
Classifier: Operating System :: OS Independent
Classifier: Intended Audience :: Developers
Classifier: Topic :: Office/Business :: Financial
Classifier: Topic :: Office/Business :: Financial :: Investment
Classifier: Topic :: Scientific/Engineering :: Interface Engine/Protocol Translator
Classifier: Topic :: Software Development :: Libraries
Classifier: Topic :: Software Development :: Libraries :: Python Modules
Classifier: Programming Language :: Python :: 3
Requires-Python: >=3.7
License-File: LICENSE
Requires-Dist: docopt (>=0.6.2)
Requires-Dist: pandas (>=1.2.2)
Requires-Dist: numpy (>=1.20.1)
Requires-Dist: pyarrow (>=3.0.0)
Requires-Dist: requests
Requires-Dist: tqdm
Provides-Extra: test
Requires-Dist: pandas-stubs (==1.2.0.39) ; extra == 'test'
Requires-Dist: pytest (==5.1.2) ; extra == 'test'
Requires-Dist: pytest-cov (==2.7.1) ; extra == 'test'
Requires-Dist: pytest-flake8 (==1.0.6) ; extra == 'test'
Requires-Dist: pytest-mypy (==0.4.0) ; extra == 'test'
Requires-Dist: pydocstyle (==4.0.1) ; extra == 'test'
Requires-Dist: pep8-naming (==0.8.1) ; extra == 'test'
Requires-Dist: pytest-docstyle (==2.0.0) ; extra == 'test'
Requires-Dist: flake8 (==3.8.1) ; extra == 'test'
